{"guzzo":{"Mega-Plex Taschereau 18 (IMAX)":{"adress":"3572, boulevard Taschereau, Greenfield Park (Québec), J4V 2H7","films":[{"langue":["en","fr"],"name":"Annie"},{"langue":["en","fr"],"name":"Big Hero 6"},{"langue":["en","fr"],"name":"Exodus: Gods and Kings"},{"langue":["en","fr"],"name":"Exodus: Gods and Kings 3D"},{"langue":["fr"],"name":"Fêtez la Danse Opéra national de Paris"},{"langue":["en"],"name":"Horrible Bosses 2"},{"langue":["en","fr"],"name":"Hubble 3D IMAX"},{"langue":["en"],"name":"Interstellar"},{"langue":["fr"],"name":"Dans les bois (version originale sous-titres francais)"},{"langue":["fr"],"name":"Les maîtres du suspense"},{"langue":["en","fr"],"name":"Night at the Museum: Secret of the Tomb"},{"langue":["en","fr"],"name":"The Gambler"},{"langue":["en","fr"],"name":"The Hobbit: The Battle of the Five Armies"},{"langue":["en","fr"],"name":"The Hobbit: The Battle of the Five Armies 3D"},{"langue":["en","fr"],"name":"The Hobbit: The Battle of the Five Armies An IMAX 3D Experience"},{"langue":["en","fr"],"name":"The Hunger Games: Mockingjay - Part 1"},{"langue":["en","fr"],"name":"The Penguins of Madagascar"},{"langue":["en","fr"],"name":"Unbroken"}],"name":"Mega-Plex Taschereau 18 (IMAX)"},"Mega-Plex Marché Central 18 (IMAX)":{"adress":"901 Crémazie Ouest, Montréal (Québec), H4N 3M5","films":[{"langue":["en","fr"],"name":"Annie"},{"langue":["fr"],"name":"Les nouveaux héros"},{"langue":["en","fr"],"name":"Exodus: Gods and Kings"},{"langue":["en","fr"],"name":"Exodus: Gods and Kings 3D"},{"langue":["fr"],"name":"Fêtez la Danse Opéra national de Paris"},{"langue":["en","fr"],"name":"Hubble 3D IMAX"},{"langue":["en"],"name":"Interstellar"},{"langue":["fr"],"name":"Dans les bois (version originale sous-titres francais)"},{"langue":["fr"],"name":"Les maîtres du suspense"},{"langue":["en","fr"],"name":"Night at the Museum: Secret of the Tomb"},{"langue":["en","fr"],"name":"The Gambler"},{"langue":["en","fr"],"name":"The Hobbit: The Battle of the Five Armies"},{"langue":["en","fr"],"name":"The Hobbit: The Battle of the Five Armies 3D"},{"langue":["en","fr"],"name":"The Hobbit: The Battle of the Five Armies An IMAX 3D Experience"},{"langue":["en","fr"],"name":"The Hunger Games: Mockingjay - Part 1"},{"langue":["en","fr"],"name":"The Penguins of Madagascar"},{"langue":["en"],"name":"Top Five"},{"langue":["en","fr"],"name":"Unbroken"}],"name":"Mega-Plex Marché Central 18 (IMAX)"},"Mega-Plex Pont-Viau 16 (IMAX)":{"adress":"1055, boulevard des Laurentides, Pont-Viau, Laval (Québec), H7G 2W2","films":[{"langue":["fr"],"name":"Annie vf"},{"langue":["fr"],"name":"Les Grands Yeux"},{"langue":["fr"],"name":"Les nouveaux héros"},{"langue":["fr"],"name":"L'Exode : dieux et rois"},{"langue":["fr"],"name":"L'Exode : dieux et rois 3D"},{"langue":["fr"],"name":"Fêtez la Danse Opéra national de Paris"},{"langue":["fr"],"name":"Hippocrate (version originale Francaise)"},{"langue":["fr"],"name":"Méchants patrons 2"},{"langue":["fr"],"name":"Hubble 3D IMAX vf"},{"langue":["fr"],"name":"Interstellaire"},{"langue":["fr"],"name":"Dans les bois (version originale sous-titres francais)"},{"langue":["fr"],"name":"Les maîtres du suspense"},{"langue":["fr"],"name":"Les Opportunistes (version italienne sous titre vf)"},{"langue":["fr"],"name":"Mommy (version originale française)"},{"langue":["fr"],"name":"UNE NUIT AU MUSÉE : LE SECRET DU TOMBEAU"},{"langue":["fr"],"name":"Le Flambeur"},{"langue":["fr"],"name":"Le Hobbit : la Bataille des Cinq Armées"},{"langue":["fr"],"name":"Le Hobbit : la Bataille des Cinq Armées 3D"},{"langue":["fr"],"name":"Le Hobbit : la Bataille des Cinq Armées: Une experience IMAX 3D"},{"langue":["fr"],"name":"Hunger Games - La Révolte : Partie 1"},{"langue":["fr"],"name":"Le Jeu de l'imitation"},{"langue":["fr"],"name":"Les Pingouins de Madagascar"},{"langue":["fr"],"name":"La Théorie De L'univers"},{"langue":["fr"],"name":"Invincible"},{"langue":["fr"],"name":"Wild vf"}],"name":"Mega-Plex Pont-Viau 16 (IMAX)"},"Mega-Plex Lacordaire 16":{"adress":"5940, des Grandes Prairies, Montréal (Québec), H1P 1A4","films":[{"langue":["en","fr"],"name":"Annie"},{"langue":["en","fr"],"name":"Big Hero 6"},{"langue":["en","fr"],"name":"Exodus: Gods and Kings"},{"langue":["en","fr"],"name":"Exodus: Gods and Kings 3D"},{"langue":["en"],"name":"Horrible Bosses 2"},{"langue":["en"],"name":"Interstellar"},{"langue":["fr"],"name":"Dans les bois (version originale sous-titres francais)"},{"langue":["fr"],"name":"Les maîtres du suspense"},{"langue":["en","fr"],"name":"Night at the Museum: Secret of the Tomb"},{"langue":["en","fr"],"name":"The Gambler"},{"langue":["en","fr"],"name":"The Hobbit: The Battle of the Five Armies"},{"langue":["en","fr"],"name":"The Hobbit: The Battle of the Five Armies 3D"},{"langue":["en","fr"],"name":"The Hunger Games: Mockingjay - Part 1"},{"langue":["en","fr"],"name":"The Penguins of Madagascar"},{"langue":["en","fr"],"name":"Unbroken"}],"name":"Mega-Plex Lacordaire 16"},"Mega-Plex Jacques-Cartier 14":{"adress":"1401, chemin Chambly, Longueuil (Québec), J4J 3X6","films":[{"langue":["fr"],"name":"Annie vf"},{"langue":["fr"],"name":"Les Grands Yeux"},{"langue":["fr"],"name":"Les nouveaux héros"},{"langue":["fr"],"name":"La Cloche et l'idiot 2"},{"langue":["fr"],"name":"L'Exode : dieux et rois"},{"langue":["fr"],"name":"L'Exode : dieux et rois 3D"},{"langue":["fr"],"name":"Hippocrate (version originale Francaise)"},{"langue":["fr"],"name":"Méchants patrons 2"},{"langue":["fr"],"name":"Interstellaire"},{"langue":["fr"],"name":"Les maîtres du suspense"},{"langue":["fr"],"name":"UNE NUIT AU MUSÉE : LE SECRET DU TOMBEAU"},{"langue":["fr"],"name":"Le Flambeur"},{"langue":["fr"],"name":"Le Hobbit : la Bataille des Cinq Armées"},{"langue":["fr"],"name":"Le Hobbit : la Bataille des Cinq Armées 3D"},{"langue":["fr"],"name":"Hunger Games - La Révolte : Partie 1"},{"langue":["fr"],"name":"Les Pingouins de Madagascar"},{"langue":["fr"],"name":"Invincible"},{"langue":["fr"],"name":"Wild vf"}],"name":"Mega-Plex Jacques-Cartier 14"},"Mega-Plex Sphèretech 14":{"adress":"3500, Côte-Vertu, Ville Saint-Laurent (Québec), H4R 1P8","films":[{"langue":["en"],"name":"Annie"},{"langue":["en"],"name":"Big Hero 6"},{"langue":["en"],"name":"Exodus: Gods and Kings"},{"langue":["en"],"name":"Exodus: Gods and Kings 3D"},{"langue":["en"],"name":"FOXCATCHER"},{"langue":["en"],"name":"Interstellar"},{"langue":["en"],"name":"Into the Woods"},{"langue":["fr"],"name":"Les maîtres du suspense"},{"langue":["en"],"name":"Night at the Museum: Secret of the Tomb"},{"langue":["en"],"name":"The Gambler"},{"langue":["en"],"name":"The Hobbit: The Battle of the Five Armies"},{"langue":["en","fr"],"name":"The Hobbit: The Battle of the Five Armies 3D"},{"langue":["en"],"name":"The Hunger Games: Mockingjay - Part 1"},{"langue":["en"],"name":"The Penguins of Madagascar"},{"langue":["en"],"name":"Top Five"},{"langue":["en"],"name":"Unbroken"},{"langue":["en"],"name":"Wild"}],"name":"Mega-Plex Sphèretech 14"},"Mega-Plex Terrebonne 14 (IMAX)":{"adress":"1071, chemin du Coteau, Terrebonne (Québec), J6W 5Y8","films":[{"langue":["fr"],"name":"Annie vf"},{"langue":["fr"],"name":"Les nouveaux héros"},{"langue":["fr"],"name":"La Cloche et l'idiot 2"},{"langue":["fr"],"name":"L'Exode : dieux et rois"},{"langue":["fr"],"name":"L'Exode : dieux et rois 3D"},{"langue":["fr"],"name":"Fêtez la Danse Opéra national de Paris"},{"langue":["fr"],"name":"Hubble 3D IMAX vf"},{"langue":["fr"],"name":"Interstellaire: Une experience IMAX"},{"langue":["fr"],"name":"Dans les bois (version originale sous-titres francais)"},{"langue":["fr"],"name":"Les maîtres du suspense"},{"langue":["fr"],"name":"UNE NUIT AU MUSÉE : LE SECRET DU TOMBEAU"},{"langue":["fr"],"name":"Le Flambeur"},{"langue":["fr"],"name":"Le Hobbit : la Bataille des Cinq Armées"},{"langue":["fr"],"name":"Le Hobbit : la Bataille des Cinq Armées 3D"},{"langue":["fr"],"name":"Le Hobbit : la Bataille des Cinq Armées: Une experience IMAX 3D"},{"langue":["fr"],"name":"Hunger Games - La Révolte : Partie 1"},{"langue":["fr"],"name":"Les Pingouins de Madagascar"},{"langue":["fr"],"name":"Invincible"}],"name":"Mega-Plex Terrebonne 14 (IMAX)"},"Mega-Plex Deux-Montagnes 14 (IMAX)":{"adress":"2701 Boul. Des Promenades, Deux Montagne (Québec), J7R 6L2","films":[{"langue":["fr"],"name":"Annie vf"},{"langue":["fr"],"name":"Les nouveaux héros"},{"langue":["fr"],"name":"La Cloche et l'idiot 2"},{"langue":["fr"],"name":"L'Exode : dieux et rois"},{"langue":["fr"],"name":"L'Exode : dieux et rois 3D"},{"langue":["fr"],"name":"Fêtez la Danse Opéra national de Paris"},{"langue":["fr"],"name":"Méchants patrons 2"},{"langue":["fr"],"name":"Hubble 3D IMAX vf"},{"langue":["fr"],"name":"Interstellaire"},{"langue":["fr"],"name":"Dans les bois (version originale sous-titres francais)"},{"langue":["fr"],"name":"Les maîtres du suspense"},{"langue":["fr"],"name":"UNE NUIT AU MUSÉE : LE SECRET DU TOMBEAU"},{"langue":["fr"],"name":"Le Flambeur"},{"langue":["fr"],"name":"Le Hobbit : la Bataille des Cinq Armées"},{"langue":["en","fr"],"name":"The Hobbit: The Battle of the Five Armies 3D"},{"langue":["fr"],"name":"Le Hobbit : la Bataille des Cinq Armées: Une experience IMAX 3D"},{"langue":["en","fr"],"name":"The Hunger Games: Mockingjay - Part 1"},{"langue":["fr"],"name":"Les Pingouins de Madagascar"},{"langue":["fr"],"name":"Invincible"}],"name":"Mega-Plex Deux-Montagnes 14 (IMAX)"},"Cinema Des Sources  (IMAX)":{"adress":"3237, boulevard Des Sources, Dollard-des-Ormeaux (Québec), H9B 1Z6","films":[{"langue":["en"],"name":"Annie"},{"langue":["en"],"name":"Big Hero 6"},{"langue":["en"],"name":"Exodus: Gods and Kings 3D"},{"langue":["en"],"name":"Horrible Bosses 2"},{"langue":["en"],"name":"Hubble 3D IMAX"},{"langue":["en"],"name":"Interstellar"},{"langue":["en"],"name":"Into the Woods"},{"langue":["en"],"name":"Night at the Museum: Secret of the Tomb"},{"langue":["en"],"name":"The Gambler"},{"langue":["en"],"name":"The Hobbit: The Battle of the Five Armies"},{"langue":["en"],"name":"The Hobbit: The Battle of the Five Armies 3D"},{"langue":["en"],"name":"The Hobbit: The Battle of the Five Armies An IMAX 3D Experience"},{"langue":["en"],"name":"The Hunger Games: Mockingjay - Part 1"},{"langue":["en"],"name":"The Penguins of Madagascar"},{"langue":["en"],"name":"Unbroken"}],"name":"Cinema Des Sources  (IMAX)"},"Cinema Sainte-Thérèse 8":{"adress":"300, rue Sicard, Sainte-Thérèse (Québec), J7E 3X5","films":[{"langue":["fr"],"name":"Annie vf"},{"langue":["fr"],"name":"Les nouveaux héros"},{"langue":["fr"],"name":"La Cloche et l'idiot 2"},{"langue":["fr"],"name":"L'Exode : dieux et rois 3D"},{"langue":["fr"],"name":"Les maîtres du suspense"},{"langue":["fr"],"name":"UNE NUIT AU MUSÉE : LE SECRET DU TOMBEAU"},{"langue":["fr"],"name":"Le Flambeur"},{"langue":["fr"],"name":"Le Hobbit : la Bataille des Cinq Armées"},{"langue":["fr"],"name":"Le Hobbit : la Bataille des Cinq Armées 3D"},{"langue":["fr"],"name":"Hunger Games - La Révolte : Partie 1"},{"langue":["fr"],"name":"Les Pingouins de Madagascar"},{"langue":["fr"],"name":"Invincible"}],"name":"Cinema Sainte-Thérèse 8"}},"odeon":{"Cinéma Cineplex Odeon Quartier Latin":{"adress":"350 rue Emery, Montreal, QC, H2X 1J1","films":[{"name":"Le Hobbit : La bataille des cinq armées","rate":"G","showtime":{"Regular":["3:00 PM","6:10 PM"],"Regular (3D)":["12:40 PM","1:20 PM","3:50 PM","7:00 PM","9:20 PM","9:45 PM"]},"time":144},{"name":"Les pingouins de Madagascar","rate":"G","showtime":{"Regular":["12:50 PM"],"Regular (3D)":["3:05 PM","5:20 PM","7:35 PM","10:00 PM"]},"time":92},{"name":"L'Exode : dieux et rois","rate":"13ans+","showtime":{"Regular":["4:00 PM"],"Regular (3D)":["12:35 PM","6:30 PM","9:40 PM"]},"time":150},{"name":"Annie (Version française)","rate":"G","showtime":{"Regular":["1:15 PM","3:45 PM","7:00 PM","9:50 PM"]},"time":119},{"name":"Foxcatcher (version française)","rate":"G","showtime":{"Regular":["12:55 PM","3:55 PM","6:55 PM","9:55 PM"]},"time":134},{"name":"Hunger Games : la révolte, partie 1","rate":"G","showtime":{"Regular":["1:25 PM","4:20 PM","7:10 PM","9:55 PM"]},"time":123},{"name":"Interstellaire (Version française)","rate":"G","showtime":{"Regular":["1:10 PM","4:55 PM","8:30 PM"]},"time":169},{"name":"La théorie de l'univers","rate":"G","showtime":{"Regular":["1:10 PM","4:00 PM","6:45 PM","9:30 PM"]},"time":123},{"name":"Le jeu de l'imitation","rate":"G","showtime":{"Regular":["1:05 PM","2:00 PM","3:45 PM","4:40 PM","6:35 PM","7:20 PM","9:15 PM","10:00 PM"]},"time":115},{"name":"Les maîtres du suspense","rate":"G","showtime":{"Regular":["12:30 PM","1:45 PM","2:50 PM","4:15 PM","5:10 PM","6:45 PM","7:35 PM","9:15 PM","10:00 PM"]},"time":101},{"name":"Les nouveaux héros","rate":"G","showtime":{"Regular":["1:40 PM","4:25 PM","7:15 PM","9:50 PM"]},"time":112},{"name":"Une nuit au musée : Le secret du tombeau","rate":"G","showtime":{"Regular":["12:30 PM","2:50 PM","5:10 PM","7:30 PM","9:50 PM"]},"time":98},{"name":"Whiplash (Anglais avec s.t.f.)","rate":"13ans+","showtime":{"Regular":["12:35 PM","4:30 PM","7:15 PM","9:45 PM"]},"time":106},{"name":"Wild (Version française)","rate":"13ans+","showtime":{"Regular":["1:30 PM","4:10 PM","6:50 PM","9:35 PM"]},"time":116}],"name":"Cinéma Cineplex Odeon Quartier Latin"},"Cinéma Banque Scotia Montréal":{"adress":"977 rue Sainte-Catherine Ouest, Montréal, QC, H3B 4W3","films":[{"name":"Exodus: Gods And Kings","rate":"13ans+","showtime":{"Regular":["12:00 PM","3:20 PM","6:40 PM","9:55 PM"],"UltraAVX (3D)":["12:40 PM","3:55 PM","7:15 PM","10:30 PM"]},"time":150},{"name":"The Hobbit: The Battle Of The Five Armies - An IMAX 3D Experience®","rate":"G","showtime":{"IMAX (3D)":["12:20 PM","3:40 PM","7:00 PM","10:20 PM"]},"time":144},{"name":"The Hobbit: The Battle Of The Five Armies","rate":"G","showtime":{"DBOX (3D)":["12:50 PM","4:10 PM","7:30 PM","10:40 PM"],"Regular":["2:10 PM","5:30 PM","8:50 PM"],"Regular (3D)":["12:50 PM","4:10 PM","7:30 PM","10:40 PM"]},"time":144},{"name":"Dumb and Dumber To","rate":"G","showtime":{"Regular":["2:00 PM","4:40 PM","7:20 PM","10:10 PM"]},"time":110},{"name":"Gone Girl","rate":"13ans+","showtime":{"Regular":["12:20 PM","3:35 PM","6:50 PM","10:15 PM"]},"time":148},{"name":"Horrible Bosses 2","rate":"13ans+","showtime":{"Regular":["2:20 PM","5:00 PM","7:45 PM","10:20 PM"]},"time":108},{"name":"Interstellar","rate":"G","showtime":{"Regular":["1:30 PM","5:10 PM","8:45 PM"]},"time":169},{"name":"The Hunger Games: Mockingjay - Part 1","rate":"G","showtime":{"Regular":["12:45 PM","1:15 PM","3:45 PM","4:15 PM","6:45 PM","7:20 PM","9:45 PM","10:25 PM"]},"time":123}],"name":"Cinéma Banque Scotia Montréal"},"Cinéma Cineplex Forum":{"adress":"2313 St. Catherine St. West Suite 101, Montréal, QC, H3H 1N2","films":[{"name":"The Imitation Game","rate":"G","showtime":{"Regular":["12:55 PM","3:50 PM","6:45 PM","9:45 PM"],"UltraAVX":["1:25 PM","4:20 PM","7:15 PM","10:15 PM"]},"time":115},{"name":"Night At The Museum: Secret Of The Tomb – The IMAX Experience®","rate":"G","showtime":{"IMAX":["12:15 PM","2:45 PM","5:15 PM","7:45 PM","10:15 PM"]},"time":98},{"name":"Big Hero 6","rate":"G","showtime":{"Regular":["12:25 PM"],"Regular (3D)":["3:10 PM","5:55 PM","8:40 PM"]},"time":112},{"name":"The Penguins of Madagascar","rate":"G","showtime":{"Regular":["12:20 PM"],"Regular (3D)":["2:45 PM","5:10 PM","7:35 PM","9:55 PM"]},"time":92},{"name":"Annie","rate":"G","showtime":{"Regular":["1:10 PM","4:10 PM","7:10 PM","10:10 PM"]},"time":119},{"name":"Back In Time (Mandarin w/Chinese & English s.t.)","rate":"G","showtime":{"Regular":["1:05 PM","3:55 PM","6:50 PM","9:40 PM"]},"time":120},{"name":"Birdman","rate":"13ans+","showtime":{"Regular":["1:00 PM","3:50 PM","6:40 PM","9:30 PM"]},"time":120},{"name":"Citizenfour","rate":"G","showtime":{"Regular":["1:00 PM","3:50 PM","6:45 PM","9:40 PM"]},"time":114},{"name":"Dear White People","rate":"G","showtime":{"Regular":["1:40 PM","4:15 PM","6:55 PM","9:30 PM"]},"time":108},{"name":"Diplomacy (French w/e.s.t.)","rate":"G","showtime":{"Regular":["1:15 PM","3:30 PM","5:45 PM","8:00 PM","10:15 PM"]},"time":88},{"name":"Foxcatcher","rate":"G","showtime":{"Regular":["12:20 PM","3:30 PM","6:45 PM","10:00 PM"]},"time":134},{"name":"Night At The Museum: Secret Of The Tomb","rate":"G","showtime":{"Regular":["1:15 PM","4:00 PM","7:00 PM","9:45 PM"]},"time":98},{"name":"PK (Hindi w/e.s.t)","rate":"G","showtime":{"Regular":["2:00 PM","5:30 PM","9:00 PM"]},"time":154},{"name":"St. Vincent","rate":"G","showtime":{"Regular":["1:50 PM","4:25 PM","7:05 PM","9:35 PM"]},"time":103},{"name":"The Good Lie","rate":"G","showtime":{"Regular":["1:35 PM","4:20 PM","7:00 PM","9:35 PM"]},"time":110},{"name":"The Masters Of Suspense (French w/e.s.t.)","rate":"G","showtime":{"Regular":["1:50 PM","4:20 PM","6:55 PM","9:30 PM"]},"time":101},{"name":"The Theory Of Everything","rate":"G","showtime":{"Regular":["1:10 PM","4:05 PM","7:00 PM","9:55 PM"]},"time":123},{"name":"Top Five","rate":"16ans+","showtime":{"Regular":["12:15 PM","2:45 PM","5:15 PM","7:45 PM","10:15 PM"]},"time":102},{"name":"Whiplash","rate":"13ans+","showtime":{"Regular":["12:15 PM","2:45 PM","5:15 PM","7:45 PM","10:15 PM"]},"time":106},{"name":"Wild","rate":"13ans+","showtime":{"Regular":["12:50 PM","1:20 PM","3:40 PM","4:10 PM","6:30 PM","7:00 PM","9:30 PM","10:00 PM"]},"time":116}],"name":"Cinéma Cineplex Forum"},"Cinéma Starcité Montréal":{"adress":"4825 avenue Pierre De Coubertin, Montréal, QC, H1V 3V4","films":[{"name":"Le Hobbit : La bataille des cinq armées","rate":"G","showtime":{"Regular":["12:25 PM","3:45 PM","7:05 PM"],"Regular (3D)":["12:00 PM","3:20 PM","6:40 PM","10:00 PM","10:25 PM"],"UltraAVX (3D)":["12:50 PM","4:10 PM","7:30 PM","10:50 PM"]},"time":144},{"name":"Les nouveaux héros","rate":"G","showtime":{"Regular":["1:15 PM"],"Regular (3D)":["4:00 PM","6:50 PM","9:40 PM"]},"time":112},{"name":"Les pingouins de Madagascar","rate":"G","showtime":{"Regular":["12:10 PM"],"Regular (3D)":["2:35 PM","4:55 PM","7:20 PM","9:45 PM"]},"time":92},{"name":"L'Exode : dieux et rois","rate":"13ans+","showtime":{"Regular (3D)":["12:20 PM","3:40 PM","7:05 PM","10:30 PM"]},"time":150},{"name":"The Hobbit: The Battle Of The Five Armies","rate":"G","showtime":{"Regular (3D)":["12:40 PM","4:00 PM","7:20 PM","10:40 PM"]},"time":144},{"name":"Annie (Version française)","rate":"G","showtime":{"Regular":["1:10 PM","4:10 PM","7:10 PM","10:10 PM"]},"time":119},{"name":"Hunger Games : la révolte, partie 1","rate":"G","showtime":{"Regular":["12:15 PM","4:15 PM","7:25 PM","10:30 PM"]},"time":123},{"name":"Interstellaire (Version française)","rate":"G","showtime":{"Regular":["12:30 PM","3:10 PM","6:50 PM","10:30 PM"]},"time":169},{"name":"La cloche et l'idiot 2","rate":"G","showtime":{"Regular":["12:00 PM","2:40 PM","5:15 PM","7:55 PM","10:35 PM"]},"time":110},{"name":"L'épreuve : Le labyrinthe","rate":"13ans+","showtime":{"Regular":["1:15 PM","4:10 PM","7:10 PM","10:00 PM"]},"time":114},{"name":"Les maîtres du suspense","rate":"G","showtime":{"Regular":["12:20 PM","2:45 PM","5:10 PM","7:40 PM","10:10 PM"]},"time":101},{"name":"Méchants patrons 2","rate":"13ans+","showtime":{"Regular":["12:10 PM","2:45 PM","5:20 PM","8:00 PM","10:40 PM"]},"time":108},{"name":"The Hunger Games: Mockingjay - Part 1","rate":"G","showtime":{"Regular":["12:55 PM","3:50 PM","7:00 PM","9:55 PM"]},"time":123},{"name":"Une nuit au musée : Le secret du tombeau","rate":"G","showtime":{"Regular":["12:15 PM","12:50 PM","2:45 PM","3:20 PM","5:15 PM","5:50 PM","7:50 PM","8:25 PM","10:20 PM","10:55 PM"]},"time":98}],"name":"Cinéma Starcité Montréal"},"Cinéma Famous Players Carrefour Angrignon":{"adress":"7077 boulevard Newman, LaSalle, QC, H8N 1X1","films":[{"name":"Le Hobbit : La bataille des cinq armées","rate":"G","showtime":{"Regular (3D)":["12:50 PM","3:55 PM","6:55 PM","10:05 PM"]},"time":144},{"name":"The Hobbit: The Battle Of The Five Armies","rate":"G","showtime":{"Regular (3D)":["12:50 PM","3:55 PM","6:55 PM","10:05 PM"]},"time":144},{"name":"Big Hero 6","rate":"G","showtime":{"Regular":["1:30 PM","4:15 PM"]},"time":112},{"name":"Horrible Bosses 2","rate":"13ans+","showtime":{"Regular":["2:00 PM","4:30 PM","7:30 PM","10:00 PM"]},"time":108},{"name":"Hunger Games : la révolte, partie 1","rate":"G","showtime":{"Regular":["6:50 PM","9:30 PM"]},"time":123},{"name":"Les maîtres du suspense","rate":"G","showtime":{"Regular":["1:30 PM","4:15 PM","7:15 PM","10:00 PM"]},"time":101},{"name":"Les pingouins de Madagascar","rate":"G","showtime":{"Regular":["1:00 PM","3:10 PM","5:25 PM","7:40 PM","9:55 PM"]},"time":92},{"name":"Night At The Museum: Secret Of The Tomb","rate":"G","showtime":{"Regular":["1:00 PM","3:15 PM","5:40 PM","8:00 PM","10:15 PM"]},"time":98},{"name":"The Hunger Games: Mockingjay - Part 1","rate":"G","showtime":{"Regular":["1:15 PM","4:00 PM","7:05 PM","9:45 PM"]},"time":123},{"name":"The Penguins of Madagascar","rate":"G","showtime":{"Regular":["12:45 PM","2:55 PM","5:10 PM","7:20 PM","9:35 PM"]},"time":92},{"name":"Une nuit au musée : Le secret du tombeau","rate":"G","showtime":{"Regular":["12:45 PM","3:00 PM","5:20 PM","7:40 PM","9:55 PM"]},"time":98}],"name":"Cinéma Famous Players Carrefour Angrignon"},"Cinéma Cineplex Odeon Cavendish Mall":{"adress":"Le Mail Cavendish, 5800 boulevard Cavendish, 5800 boulevard Cavendish, Cote Saint-Luc, QC, H4W 2T5","films":[{"name":"Exodus: Gods And Kings","rate":"13ans+","showtime":{"Regular":["3:40 PM"],"Regular (3D)":["12:30 PM","6:45 PM","9:50 PM"]},"time":150},{"name":"The Hobbit: The Battle Of The Five Armies","rate":"G","showtime":{"Regular (3D)":["12:45 PM","3:45 PM","6:50 PM","9:55 PM"]},"time":144},{"name":"Annie","rate":"G","showtime":{"Regular":["1:15 PM","4:05 PM","7:00 PM","9:35 PM"]},"time":119},{"name":"Night At The Museum: Secret Of The Tomb","rate":"G","showtime":{"Regular":["12:35 PM","2:50 PM","5:05 PM","7:20 PM","9:40 PM"]},"time":98},{"name":"St. Vincent","rate":"G","showtime":{"Regular":["1:25 PM","4:10 PM","6:55 PM","9:15 PM"]},"time":103},{"name":"The Hunger Games: Mockingjay - Part 1","rate":"G","showtime":{"Regular":["1:05 PM","4:00 PM","7:10 PM","9:50 PM"]},"time":123},{"name":"The Penguins of Madagascar","rate":"G","showtime":{"Regular":["12:50 PM","3:00 PM","5:10 PM","7:20 PM","9:30 PM"]},"time":92},{"name":"The Theory Of Everything","rate":"G","showtime":{"Regular":["1:10 PM","4:15 PM","7:05 PM","9:45 PM"]},"time":123}],"name":"Cinéma Cineplex Odeon Cavendish Mall"},"Cinéma Cineplex Odeon Boucherville":{"adress":"20 boulevard de Mortagne, Boucherville, QC, J4B 5K6","films":[{"name":"Le Hobbit : La bataille des cinq armées","rate":"G","showtime":{"Regular (3D)":["12:35 PM","3:50 PM","7:00 PM","10:05 PM"]},"time":144},{"name":"Les pingouins de Madagascar","rate":"G","showtime":{"Regular":["12:40 PM"],"Regular (3D)":["2:55 PM","5:05 PM","7:30 PM","9:45 PM"]},"time":92},{"name":"L'Exode : dieux et rois","rate":"13ans+","showtime":{"Regular":["3:40 PM"],"Regular (3D)":["12:30 PM","6:50 PM","10:00 PM"]},"time":150},{"name":"Annie (Version française)","rate":"G","showtime":{"Regular":["1:10 PM","3:55 PM","7:05 PM","9:45 PM"]},"time":119},{"name":"Diplomatie (version française)","rate":"G","showtime":{"Regular":["12:50 PM","3:00 PM","5:10 PM","7:25 PM","9:35 PM"]},"time":88},{"name":"Hunger Games : la révolte, partie 1","rate":"G","showtime":{"Regular":["1:00 PM","3:45 PM","7:10 PM","9:55 PM"]},"time":123},{"name":"La théorie de l'univers","rate":"G","showtime":{"Regular":["1:15 PM","4:05 PM","7:15 PM","10:00 PM"]},"time":123},{"name":"Les maîtres du suspense","rate":"G","showtime":{"Regular":["1:05 PM","4:10 PM","7:20 PM","9:50 PM"]},"time":101},{"name":"Les yeux jaunes des crocodiles","rate":"G","showtime":{"Regular":["12:55 PM","4:00 PM","6:55 PM","9:40 PM"]},"time":123},{"name":"Une nuit au musée : Le secret du tombeau","rate":"G","showtime":{"Regular":["12:45 PM","3:00 PM","5:15 PM","7:35 PM","9:55 PM"]},"time":98}],"name":"Cinéma Cineplex Odeon Boucherville"},"Cinéma Cineplex Odeon Place La Salle":{"adress":"7816 Boulevard Champlain, Local 62, LaSalle, QC, H8P 1B3","films":[{"name":"Exodus: Gods And Kings","rate":"13ans+","showtime":{"Regular":["3:35 PM"],"Regular (3D)":["12:30 PM","6:45 PM","9:50 PM"]},"time":150},{"name":"L'Exode : dieux et rois","rate":"13ans+","showtime":{"Regular":["3:40 PM"],"Regular (3D)":["12:35 PM","6:50 PM","9:55 PM"]},"time":150},{"name":"Annie","rate":"G","showtime":{"Regular":["12:50 PM","3:50 PM","6:55 PM","9:30 PM"]},"time":119},{"name":"Annie (Version française)","rate":"G","showtime":{"Regular":["1:05 PM","4:05 PM","7:05 PM","9:35 PM"]},"time":119},{"name":"Gone Girl","rate":"13ans+","showtime":{"Regular":["1:20 PM","4:25 PM","7:30 PM"]},"time":148},{"name":"Hunger Games : la révolte, partie 1","rate":"G","showtime":{"Regular":["7:05 PM","9:45 PM"]},"time":123},{"name":"Interstellar","rate":"G","showtime":{"Regular":["1:00 PM","4:30 PM","8:00 PM"]},"time":169},{"name":"Le Hobbit : La bataille des cinq armées","rate":"G","showtime":{"Regular":["12:55 PM","3:55 PM","6:55 PM","9:55 PM"]},"time":144},{"name":"Les maîtres du suspense","rate":"G","showtime":{"Regular":["1:25 PM","4:20 PM","7:15 PM","9:40 PM"]},"time":101},{"name":"Les pingouins de Madagascar","rate":"G","showtime":{"Regular":["1:30 PM","4:15 PM"]},"time":92},{"name":"The Hobbit: The Battle Of The Five Armies","rate":"G","showtime":{"Regular":["12:40 PM","3:45 PM","6:50 PM","9:50 PM"]},"time":144},{"name":"The Hunger Games: Mockingjay - Part 1","rate":"G","showtime":{"Regular":["1:00 PM","4:00 PM","7:00 PM","9:40 PM"]},"time":123},{"name":"The Penguins of Madagascar","rate":"G","showtime":{"Regular":["1:05 PM","3:15 PM","5:20 PM","7:30 PM","9:45 PM"]},"time":92}],"name":"Cinéma Cineplex Odeon Place La Salle"},"Cinéma Cineplex Odeon Brossard et Cinéma VIP":{"adress":"9350 boulevard Leduc, Brossard, QC, J4Y 0B3","films":[{"name":"Exodus: Gods And Kings","rate":"13ans+","showtime":{"Regular":["4:00 PM"],"Regular (3D)":["12:45 PM","7:15 PM","10:30 PM"],"VIP (18+) (3D)":["4:30 PM","8:15 PM"]},"time":150},{"name":"Le Hobbit : La bataille des cinq armées","rate":"G","showtime":{"Regular (3D)":["1:00 PM","4:15 PM","7:30 PM","10:45 PM"],"UltraAVX (3D)":["12:30 PM","3:45 PM","7:00 PM","10:15 PM"],"VIP (18+) (3D)":["3:30 PM","7:00 PM","10:30 PM"]},"time":144},{"name":"The Hobbit: The Battle Of The Five Armies","rate":"G","showtime":{"DBOX (3D)":["12:45 PM","4:00 PM","7:15 PM","10:30 PM"],"Regular":["2:00 PM"],"Regular (3D)":["6:30 PM","9:40 PM"],"VIP (18+) (3D)":["3:00 PM","6:30 PM","9:45 PM"]},"time":144},{"name":"Les maîtres du suspense","rate":"G","showtime":{"Regular":["12:45 PM","3:10 PM","5:35 PM","8:00 PM","10:25 PM"],"VIP (18+)":["4:00 PM","7:30 PM","10:15 PM"]},"time":101},{"name":"Les pingouins de Madagascar","rate":"G","showtime":{"Regular":["1:00 PM"],"Regular (3D)":["3:30 PM","6:00 PM","8:15 PM","10:40 PM"]},"time":92},{"name":"L'Exode : dieux et rois","rate":"13ans+","showtime":{"Regular":["3:45 PM"],"Regular (3D)":["12:30 PM","7:00 PM","10:15 PM"]},"time":150},{"name":"Annie (Version française)","rate":"G","showtime":{"Regular":["1:15 PM","4:15 PM","7:15 PM","10:15 PM"]},"time":119},{"name":"Hunger Games : la révolte, partie 1","rate":"G","showtime":{"Regular":["6:45 PM","9:45 PM"]},"time":123},{"name":"Interstellaire (Version française)","rate":"G","showtime":{"Regular":["1:45 PM","6:00 PM","9:45 PM"]},"time":169},{"name":"La cloche et l'idiot 2","rate":"G","showtime":{"Regular":["1:00 PM","3:45 PM","6:45 PM","9:30 PM"]},"time":110},{"name":"La théorie de l'univers","rate":"G","showtime":{"Regular":["1:45 PM","4:35 PM","7:30 PM","10:30 PM"]},"time":123},{"name":"Les nouveaux héros","rate":"G","showtime":{"Regular":["1:30 PM","4:15 PM","7:00 PM","9:45 PM"]},"time":112},{"name":"The Hunger Games: Mockingjay - Part 1","rate":"G","showtime":{"Regular":["12:45 PM","4:00 PM","7:30 PM","10:30 PM"]},"time":123},{"name":"The Penguins of Madagascar","rate":"G","showtime":{"Regular":["1:30 PM","4:00 PM"]},"time":92},{"name":"Une nuit au musée : Le secret du tombeau","rate":"G","showtime":{"Regular":["12:30 PM","3:00 PM","5:30 PM","8:00 PM","10:30 PM"]},"time":98}],"name":"Cinéma Cineplex Odeon Brossard et Cinéma VIP"},"Cinéma Cineplex Odeon St-Bruno":{"adress":"1495 boulevard St-Bruno, St-Bruno, QC, J3V 6J1","films":[{"name":"Le Hobbit : La bataille des cinq armées","rate":"G","showtime":{"Regular":["7:15 PM"],"Regular (3D)":["12:30 PM","1:00 PM","3:45 PM","4:15 PM","7:00 PM","9:30 PM","10:00 PM"]},"time":144},{"name":"Les pingouins de Madagascar","rate":"G","showtime":{"Regular":["12:35 PM"],"Regular (3D)":["2:45 PM","4:55 PM","7:10 PM","10:10 PM"]},"time":92},{"name":"L'Exode : dieux et rois","rate":"13ans+","showtime":{"Regular":["4:45 PM"],"Regular (3D)":["1:15 PM","8:00 PM"]},"time":150},{"name":"Annie (Version française)","rate":"G","showtime":{"Regular":["12:55 PM","3:55 PM","7:15 PM","9:50 PM"]},"time":119},{"name":"Hunger Games : la révolte, partie 1","rate":"G","showtime":{"Regular":["1:20 PM","4:10 PM","6:55 PM","9:45 PM"]},"time":123},{"name":"Interstellaire (Version française)","rate":"G","showtime":{"Regular":["1:10 PM","4:40 PM","8:10 PM"]},"time":169},{"name":"La cloche et l'idiot 2","rate":"G","showtime":{"Regular":["1:30 PM","4:10 PM","7:30 PM","9:55 PM"]},"time":110},{"name":"Les maîtres du suspense","rate":"G","showtime":{"Regular":["12:45 PM","3:05 PM","5:25 PM","7:45 PM","10:05 PM"]},"time":101},{"name":"Les nouveaux héros","rate":"G","showtime":{"Regular":["1:25 PM","4:00 PM","7:15 PM","9:40 PM"]},"time":112},{"name":"Une nuit au musée : Le secret du tombeau","rate":"G","showtime":{"Regular":["12:40 PM","2:55 PM","5:15 PM","7:35 PM","9:50 PM"]},"time":98}],"name":"Cinéma Cineplex Odeon St-Bruno"},"Cinéma Cineplex Odeon Delson":{"adress":"47 boulevard Georges-Gagné, Delson, QC, J5B 2E5","films":[{"name":"Le Hobbit : La bataille des cinq armées","rate":"G","showtime":{"Regular (3D)":["12:50 PM","3:50 PM","6:50 PM","9:50 PM"]},"time":144},{"name":"L'Exode : dieux et rois","rate":"13ans+","showtime":{"Regular":["3:35 PM"],"Regular (3D)":["12:30 PM","6:40 PM","9:45 PM"]},"time":150},{"name":"Annie (Version française)","rate":"G","showtime":{"Regular":["1:10 PM","3:45 PM","7:00 PM","9:35 PM"]},"time":119},{"name":"Hunger Games : la révolte, partie 1","rate":"G","showtime":{"Regular":["1:00 PM","3:55 PM","6:45 PM","9:25 PM"]},"time":123},{"name":"Les maîtres du suspense","rate":"G","showtime":{"Regular":["1:15 PM","3:30 PM","7:25 PM","9:40 PM"]},"time":101},{"name":"Les pingouins de Madagascar","rate":"G","showtime":{"Regular":["12:40 PM","2:50 PM","5:00 PM","7:10 PM","9:20 PM"]},"time":92},{"name":"Une nuit au musée : Le secret du tombeau","rate":"G","showtime":{"Regular":["12:45 PM","3:00 PM","5:15 PM","7:40 PM","9:55 PM"]},"time":98}],"name":"Cinéma Cineplex Odeon Delson"},"Cinéma Colossus Laval":{"adress":"2800 avenue Du Cosmodôme, Laval, QC, H7T 2X1","films":[{"name":"The Hobbit: The Battle Of The Five Armies","rate":"G","showtime":{"DBOX":["3:15 PM","6:30 PM"],"DBOX (3D)":["12:00 PM","9:50 PM"],"Regular":["3:15 PM","6:30 PM"],"Regular (3D)":["12:00 PM","9:50 PM"],"UltraAVX (3D)":["12:50 PM","4:10 PM","7:30 PM","10:40 PM"]},"time":144},{"name":"Exodus: Gods And Kings","rate":"13ans+","showtime":{"Regular":["4:00 PM"],"Regular (3D)":["12:40 PM","7:20 PM","10:40 PM"]},"time":150},{"name":"Le Hobbit : La bataille des cinq armées","rate":"G","showtime":{"Regular":["2:40 PM","6:00 PM"],"Regular (3D)":["9:20 PM"]},"time":144},{"name":"Les pingouins de Madagascar","rate":"G","showtime":{"Regular":["12:45 PM"],"Regular (3D)":["3:10 PM","5:35 PM","8:00 PM","10:25 PM"]},"time":92},{"name":"L'Exode : dieux et rois","rate":"13ans+","showtime":{"Regular":["3:35 PM"],"Regular (3D)":["12:15 PM","7:00 PM","10:20 PM"]},"time":150},{"name":"The Penguins of Madagascar","rate":"G","showtime":{"Regular":["12:00 PM"],"Regular (3D)":["2:20 PM","4:45 PM","7:10 PM","9:45 PM"]},"time":92},{"name":"Annie","rate":"G","showtime":{"Regular":["1:10 PM","4:10 PM","7:10 PM","10:10 PM"]},"time":119},{"name":"Big Hero 6","rate":"G","showtime":{"Regular":["1:30 PM","4:20 PM"]},"time":112},{"name":"Dumb and Dumber To","rate":"G","showtime":{"Regular":["7:20 PM","10:05 PM"]},"time":110},{"name":"Horrible Bosses 2","rate":"13ans+","showtime":{"Regular":["2:00 PM","5:00 PM","8:00 PM","10:45 PM"]},"time":108},{"name":"Hunger Games : la révolte, partie 1","rate":"G","showtime":{"Regular":["1:10 PM","4:10 PM","7:10 PM","10:10 PM"]},"time":123},{"name":"Interstellar","rate":"G","showtime":{"Regular":["6:30 PM","10:15 PM"]},"time":169},{"name":"Les maîtres du suspense","rate":"G","showtime":{"Regular":["12:15 PM","2:50 PM","5:30 PM","8:10 PM","10:45 PM"]},"time":101},{"name":"Les nouveaux héros","rate":"G","showtime":{"Regular":["1:00 PM","3:45 PM"]},"time":112},{"name":"Night At The Museum: Secret Of The Tomb","rate":"G","showtime":{"Regular":["12:15 PM","2:45 PM","5:15 PM","7:50 PM","10:20 PM"]},"time":98},{"name":"The Hunger Games: Mockingjay - Part 1","rate":"G","showtime":{"Regular":["1:30 PM","4:30 PM","7:35 PM","10:35 PM"]},"time":123},{"name":"Top Five","rate":"16ans+","showtime":{"Regular":["12:10 PM","2:40 PM","5:10 PM","7:50 PM","10:30 PM"]},"time":102},{"name":"Une nuit au musée : Le secret du tombeau","rate":"G","showtime":{"Regular":["12:00 PM","2:30 PM","5:00 PM","7:30 PM","10:00 PM"]},"time":98}],"name":"Cinéma Colossus Laval"}}}